README.md
setup.py
django_requestuser.egg-info/PKG-INFO
django_requestuser.egg-info/SOURCES.txt
django_requestuser.egg-info/dependency_links.txt
django_requestuser.egg-info/not-zip-safe
django_requestuser.egg-info/top_level.txt
requestuser/__init__.py
requestuser/requestuser.py